openroboadvisor/__init__.py
openroboadvisor/advisor/__init__.py
openroboadvisor/advisor/asset_class_advisor.py
openroboadvisor/advisor/base_advisor.py
openroboadvisor/advisor/simple_advisor.py
openroboadvisor/advisor/suggestion.py
openroboadvisor/ledger/__init__.py
openroboadvisor/ledger/account.py
openroboadvisor/ledger/asset.py
openroboadvisor/ledger/entry.py
openroboadvisor/ledger/ledger.py
openroboadvisor/portfolio/__init__.py
openroboadvisor/portfolio/account.py
openroboadvisor/portfolio/portfolio.py
open_robo_advisor-0.1.0.dist-info/WHEEL
open_robo_advisor-0.1.0.dist-info/METADATA
open_robo_advisor-0.1.0.dist-info/license_files/LICENSE
open_robo_advisor-0.1.0.dist-info/RECORD
