Metadata-Version: 2.1
Name: open-robo-advisor
Version: 0.1.0
Summary: Open Robo-Advisor is an open source robo-advisor engine written in Python.
License: MIT
Author-email: Chris Riccomini <criccomini@apache.org>
Requires-Python: >=3.10
Project-URL: Homepage, https://github.com/highwire-ai/open-robo-advisor
